ket/__init__.py
ket/amazon.py
ket/base.py
ket/expv.py
ket/gates.py
ket/ibm.py
ket/npsim.py
ket/operations.py
ket/quantumstate.py
ket/quforge.py
ket/remote.py
ket/clib/__init__.py
ket/clib/kbw.py
ket/clib/libket.py
ket/clib/wrapper.py
ket/clib/libs/__init__.py
ket/clib/libs/libkbw.dylib
ket/clib/libs/libket.dylib
ket/qulib/__init__.py
ket/qulib/gates.py
ket/qulib/ham.py
ket/qulib/math.py
ket/qulib/oracle.py
ket/qulib/prepare.py
ket_lang-0.9.2.dist-info/licenses/LICENSE
ket_lang-0.9.2.dist-info/METADATA
ket_lang-0.9.2.dist-info/WHEEL
ket_lang-0.9.2.dist-info/top_level.txt
ket_lang-0.9.2.dist-info/RECORD
