Metadata-Version: 2.4
Name: ket-lang
Version: 0.9.2
Summary: Ket quantum programming language interpreter and library
Home-page: https://quantumket.org
Author: Evandro Chagas Ribeiro da Rosa
Author-email: evandro@quantuloop.com
License: Apache-2.0
Project-URL: Source, https://gitlab.com/quantum-ket/ket
Keywords: quantum computer,quantum programming,quantum simulator
Platform: linux
Platform: win32
Platform: osx
Classifier: Intended Audience :: Science/Research
Classifier: Operating System :: POSIX :: Linux
Classifier: Operating System :: Microsoft :: Windows
Classifier: Operating System :: MacOS
Classifier: Programming Language :: Python :: 3
Classifier: Programming Language :: Rust
Requires-Python: >=3.10
License-File: LICENSE
Provides-Extra: amazon
Requires-Dist: amazon-braket-sdk; extra == "amazon"
Provides-Extra: ibm
Requires-Dist: qiskit<3.0,>=2.0.0; extra == "ibm"
Requires-Dist: qiskit-aer; extra == "ibm"
Requires-Dist: qiskit-ibm-runtime; extra == "ibm"
Provides-Extra: plot
Requires-Dist: numpy; extra == "plot"
Requires-Dist: plotly; extra == "plot"
Requires-Dist: pandas; extra == "plot"
Requires-Dist: nbformat; extra == "plot"
Requires-Dist: kaleido; extra == "plot"
Requires-Dist: qiskit[visualization]<3.0,>=2.0.0; extra == "plot"
Provides-Extra: remote
Requires-Dist: requests; extra == "remote"
Requires-Dist: PyJWT[crypto]; extra == "remote"
Requires-Dist: bcrypt; extra == "remote"
Provides-Extra: qml
Requires-Dist: quforge==0.3.5; extra == "qml"
Dynamic: license-file
